<?xml version="1.0" encoding="utf-8" ?>
<dwsync>
<file name="form_ingreso.html" server="ftp.planidear.com.ar" local="133037723090294885" remote="133037725200000000" Dst="0" />
<file name="help.html" server="ftp.planidear.com.ar" local="133037753699473456" remote="133037755800000000" Dst="0" />
<file name="index.html" server="ftp.planidear.com.ar" local="133037708397784271" remote="133037710800000000" Dst="0" />
<file name="MapaSitio.jpeg" server="ftp.planidear.com.ar" local="132989198479909817" remote="132992848200000000" Dst="0" />
<file name="plantilla.html" server="ftp.planidear.com.ar" local="132989198481923363" remote="132992848200000000" Dst="0" />
<file name="sobre_nosotros.html" server="ftp.planidear.com.ar" local="133037715987620490" remote="133037718600000000" Dst="0" />
<file name="InsUsuario.php" server="ftp.planidear.com.ar" local="133037664098023723" remote="133037666400000000" Dst="0" />
<file name="EnvCorreo.php" server="ftp.planidear.com.ar" local="133037661629766798" remote="133037664000000000" Dst="0" />
<file name="contacto.html" server="ftp.planidear.com.ar" local="133037724257078335" remote="133037726400000000" Dst="0" />
<file name="Logeado.php" server="ftp.planidear.com.ar" local="133037664984587054" remote="133037667600000000" Dst="0" />
<file name="mapa del sitio.png" server="ftp.planidear.com.ar" local="132989198481918064" remote="132992848200000000" Dst="0" />
<file name="scriptGim.sql" server="ftp.planidear.com.ar" local="132989198481933551" remote="132992848200000000" Dst="0" />
<file name="sobre_nosotros_old_v1.html" server="ftp.planidear.com.ar" local="132989198481952837" remote="132992848200000000" Dst="0" />
<file name="sobre_nosotros_v3.html" server="ftp.planidear.com.ar" local="132989198481962812" remote="132992848200000000" Dst="0" />
<file name="alta_cliente.html" server="ftp.planidear.com.ar" local="133037660862104538" remote="133037663400000000" Dst="0" />
<file name="form_registro.html" server="ftp.planidear.com.ar" local="133037736145231887" remote="133037738400000000" Dst="0" />
<file name="sobre_nosotros-Final.html" server="ftp.planidear.com.ar" local="132989198481942880" remote="132992848200000000" Dst="0" />
<file name="ListadoUsuarios.php" server="ftp.planidear.com.ar" local="132989198479896912" remote="132992848200000000" Dst="0" />
<file name="LisUsuarios.php" server="ftp.planidear.com.ar" local="133037664642371157" remote="133037667000000000" Dst="0" />
<file name="check_list.html" server="ftp.planidear.com.ar" local="132989198479939664" remote="132992848200000000" Dst="0" />
<file name="PrRelaciones.png" server="ftp.planidear.com.ar" local="132989185662127831" remote="132992848200000000" Dst="0" />
<file name="TablaGit.xlsx" server="ftp.planidear.com.ar" local="132989198479924596" remote="132992848200000000" Dst="0" />
<file name="ecommerce.html" server="ftp.planidear.com.ar" local="133037776650665282" remote="133037779200000000" Dst="0" />
</dwsync>